setup.py
Kosta_distributions/Binomialdistribution.py
Kosta_distributions/Gaussiandistribution.py
Kosta_distributions/Generaldistribution.py
Kosta_distributions/__init__.py
Kosta_distributions.egg-info/PKG-INFO
Kosta_distributions.egg-info/SOURCES.txt
Kosta_distributions.egg-info/dependency_links.txt
Kosta_distributions.egg-info/not-zip-safe
Kosta_distributions.egg-info/top_level.txt